masc/__init__.py
masc/cms.py
masc/constants.py
masc/custom.py
masc/dictionary.py
masc/drupal.py
masc/joomla.py
masc/main.py
masc/masc.conf
masc/masc_entry.py
masc/masc_utils.py
masc/print_utils.py
masc/wordpress.py
masc/dicts/custom_suspect_content.data
masc/dicts/custom_suspect_files.data
masc/dicts/drupal_suspect_content.data
masc/dicts/drupal_suspect_files.data
masc/dicts/wordpress_suspect_content.data
masc/dicts/wordpress_suspect_files.data
masc/signatures/checksum/bofhland_malware_attach.hdb.json
masc/signatures/checksum/crdfam.clamav.hdb.json
masc/signatures/checksum/doppelstern.hdb.json
masc/signatures/checksum/malwarehash.hsb.json
masc/signatures/checksum/porcupine.hsb.json
masc/signatures/checksum/rfxn_lmd.json
masc/signatures/checksum/vx_0.json
masc/signatures/checksum/vx_1.json
masc/signatures/checksum/vx_10.json
masc/signatures/checksum/vx_100.json
masc/signatures/checksum/vx_101.json
masc/signatures/checksum/vx_102.json
masc/signatures/checksum/vx_103.json
masc/signatures/checksum/vx_104.json
masc/signatures/checksum/vx_105.json
masc/signatures/checksum/vx_106.json
masc/signatures/checksum/vx_107.json
masc/signatures/checksum/vx_108.json
masc/signatures/checksum/vx_109.json
masc/signatures/checksum/vx_11.json
masc/signatures/checksum/vx_110.json
masc/signatures/checksum/vx_111.json
masc/signatures/checksum/vx_112.json
masc/signatures/checksum/vx_113.json
masc/signatures/checksum/vx_114.json
masc/signatures/checksum/vx_115.json
masc/signatures/checksum/vx_116.json
masc/signatures/checksum/vx_117.json
masc/signatures/checksum/vx_118.json
masc/signatures/checksum/vx_119.json
masc/signatures/checksum/vx_12.json
masc/signatures/checksum/vx_120.json
masc/signatures/checksum/vx_121.json
masc/signatures/checksum/vx_122.json
masc/signatures/checksum/vx_123.json
masc/signatures/checksum/vx_124.json
masc/signatures/checksum/vx_125.json
masc/signatures/checksum/vx_126.json
masc/signatures/checksum/vx_127.json
masc/signatures/checksum/vx_128.json
masc-0.3.1.dist-info/LICENSE.txt
masc-0.3.1.dist-info/METADATA
masc-0.3.1.dist-info/WHEEL
masc-0.3.1.dist-info/entry_points.txt
masc-0.3.1.dist-info/top_level.txt
masc-0.3.1.dist-info/RECORD
