Metadata-Version: 2.1
Name: masc
Version: 0.3.1
Summary: A malware web scanner
Home-page: https://github.com/sfaci/masc
Author: Santiago Faci
Author-email: santi@arkabytes.com
License: UNKNOWN
Keywords: malware scanner security
Platform: UNKNOWN
Classifier: Development Status :: 3 - Alpha
Classifier: License :: OSI Approved :: GNU General Public License v3 (GPLv3)
